djangocms_timed/__init__.py
djangocms_timed/cms_plugins.py
djangocms_timed/models.py
djangocms_timed/locale/de/LC_MESSAGES/django.mo
djangocms_timed/locale/de/LC_MESSAGES/django.po
djangocms_timed/locale/en/LC_MESSAGES/django.mo
djangocms_timed/locale/en/LC_MESSAGES/django.po
djangocms_timed/migrations/0001_initial.py
djangocms_timed/migrations/__init__.py
djangocms_timed/templates/djangocms_timed/timed.html
tests/__init__.py
tests/settings.py
tests/test_plugins.py
djangocms_timed_new-2.0.1.dist-info/LICENSE.txt
djangocms_timed_new-2.0.1.dist-info/METADATA
djangocms_timed_new-2.0.1.dist-info/WHEEL
djangocms_timed_new-2.0.1.dist-info/top_level.txt
djangocms_timed_new-2.0.1.dist-info/RECORD
