Metadata-Version: 2.1
Name: djangocms-timed-new
Version: 2.0.1
Summary: Timed addon for django CMS
Home-page: https://github.com/arjan-s/djangocms-timed
Author: arjan5
Author-email: arjan@anymore.nl
License: BSD License
Platform: OS Independent
Classifier: Development Status :: 4 - Beta
Classifier: Environment :: Web Environment
Classifier: Framework :: Django
Classifier: Intended Audience :: Developers
Classifier: License :: OSI Approved :: BSD License
Classifier: Operating System :: OS Independent
Classifier: Programming Language :: Python
Classifier: Topic :: Internet :: WWW/HTTP :: Dynamic Content
Classifier: Topic :: Software Development
Classifier: Topic :: Software Development :: Libraries :: Application Frameworks
License-File: LICENSE.txt
Requires-Dist: django (>=2.2)
Requires-Dist: django-cms (>=3.7)
